jrt_laser_distance_sensor/__init__.py
jrt_laser_distance_sensor/__main__.py
jrt_laser_distance_sensor/jrtserial.py
jrt_laser_distance_sensor-0.0.5.dist-info/LICENSE.txt
jrt_laser_distance_sensor-0.0.5.dist-info/METADATA
jrt_laser_distance_sensor-0.0.5.dist-info/WHEEL
jrt_laser_distance_sensor-0.0.5.dist-info/entry_points.txt
jrt_laser_distance_sensor-0.0.5.dist-info/top_level.txt
jrt_laser_distance_sensor-0.0.5.dist-info/RECORD
