Metadata-Version: 2.1
Name: jrt-laser-distance-sensor
Version: 0.0.5
Summary: A python package to interface with serial laser distance sensors fron Chengdu JRT Meter Technology Co., Ltd.
Author-email: Christopher Sedore <cmsedore@gmail.com>
Project-URL: Homepage, https://github.com/cmsedore/jrt-laser-distance-sensor
Project-URL: Bug Tracker, https://github.com/cmsedore/jrt-laser-distance-sensor/issues
Classifier: Programming Language :: Python :: 3
Classifier: License :: OSI Approved :: MIT License
Classifier: Operating System :: OS Independent
Requires-Python: >=3.8
License-File: LICENSE.txt
Requires-Dist: pyserial >=3.5
